ppef.cpython-39-darwin.so
ppef-1.0.2.dist-info/RECORD
ppef-1.0.2.dist-info/WHEEL
ppef-1.0.2.dist-info/top_level.txt
ppef-1.0.2.dist-info/METADATA
ppef-1.0.2.dist-info/licenses/LICENSE
